{"_default": {"1": {"id": "PSA.86", "bibleId": "bf8f1c7f3f9045a5-01", "number": "86", "bookId": "PSA", "reference": "Psalms 86", "copyright": "PUBLIC DOMAIN", "content": [{"name": "para", "type": "tag", "attrs": {"style": "p"}, "items": [{"text": "A Prayer of David. Incline Thine ear, O LORD, and answer me; for I am poor and needy. ", "type": "text", "attrs": {"verseId": "PSA.86.1", "verseOrgIds": ["PSA.86.1"]}}, {"text": "Keep my soul, for I am godly; O Thou my God, save Thy servant that trusteth in Thee. ", "type": "text", "attrs": {"verseId": "PSA.86.2", "verseOrgIds": ["PSA.86.2"]}}, {"text": "Be gracious unto me, O Lord; for unto Thee do I cry all the day. ", "type": "text", "attrs": {"verseId": "PSA.86.3", "verseOrgIds": ["PSA.86.3"]}}, {"text": "Rejoice the soul of Thy servant; for unto Thee, O Lord, do I lift up my soul. ", "type": "text", "attrs": {"verseId": "PSA.86.4", "verseOrgIds": ["PSA.86.4"]}}, {"text": "For Thou, Lord, art good, and ready to pardon, and plenteous in mercy unto all them that call upon Thee. ", "type": "text", "attrs": {"verseId": "PSA.86.5", "verseOrgIds": ["PSA.86.5"]}}, {"text": "Give ear, O LORD, unto my prayer; and attend unto the voice of my supplications. ", "type": "text", "attrs": {"verseId": "PSA.86.6", "verseOrgIds": ["PSA.86.6"]}}, {"text": "In the day of my trouble I call upon Thee; for Thou wilt answer me. ", "type": "text", "attrs": {"verseId": "PSA.86.7", "verseOrgIds": ["PSA.86.7"]}}, {"text": "There is none like unto Thee among the gods, O Lord, and there are no works like Thine. ", "type": "text", "attrs": {"verseId": "PSA.86.8", "verseOrgIds": ["PSA.86.8"]}}, {"text": "All nations whom Thou hast made shall come and prostrate themselves before Thee, O Lord; and they shall glorify Thy name. ", "type": "text", "attrs": {"verseId": "PSA.86.9", "verseOrgIds": ["PSA.86.9"]}}, {"text": "For Thou art great, and doest wondrous things; Thou art God alone. ", "type": "text", "attrs": {"verseId": "PSA.86.10", "verseOrgIds": ["PSA.86.10"]}}, {"text": "Teach me, O LORD, Thy way, that I may walk in Thy truth; make one my heart to fear Thy name. ", "type": "text", "attrs": {"verseId": "PSA.86.11", "verseOrgIds": ["PSA.86.11"]}}, {"text": "I will thank Thee, O Lord my God, with my whole heart; and I will glorify Thy name for evermore. ", "type": "text", "attrs": {"verseId": "PSA.86.12", "verseOrgIds": ["PSA.86.12"]}}, {"text": "For great is Thy mercy toward me; and Thou hast delivered my soul from the lowest nether-world. ", "type": "text", "attrs": {"verseId": "PSA.86.13", "verseOrgIds": ["PSA.86.13"]}}, {"text": "O God, the proud are risen up against me, and the company of violent men have sought after my soul, and have not set Thee before them. ", "type": "text", "attrs": {"verseId": "PSA.86.14", "verseOrgIds": ["PSA.86.14"]}}, {"text": "But Thou, O Lord, art a God full of compassion and gracious, slow to anger, and plenteous in mercy and truth. ", "type": "text", "attrs": {"verseId": "PSA.86.15", "verseOrgIds": ["PSA.86.15"]}}, {"text": "O turn unto me, and be gracious unto me; give Thy strength unto Thy servant, and save the son of Thy handmaid. ", "type": "text", "attrs": {"verseId": "PSA.86.16", "verseOrgIds": ["PSA.86.16"]}}, {"text": "Work in my behalf a sign for good; that they that hate me may see it, and be put to shame, because Thou, LORD, hast helped me, and comforted me.", "type": "text", "attrs": {"verseId": "PSA.86.17", "verseOrgIds": ["PSA.86.17"]}}]}], "next": {"id": "PSA.87", "number": "87", "bookId": "PSA"}, "previous": {"id": "PSA.85", "number": "85", "bookId": "PSA"}}}}