{"_default": {"1": {"id": "PRO.16", "bibleId": "f72b840c855f362c-04", "number": "16", "bookId": "PRO", "reference": "Proverbs 16", "copyright": "\n          \n            PUBLIC DOMAIN\n          \n        ", "content": [{"name": "para", "type": "tag", "attrs": {"style": "q1"}, "items": [{"text": "The plans of the heart belong to man,", "type": "text", "attrs": {"verseId": "PRO.16.1", "verseOrgIds": ["PRO.16.1"]}}]}, {"name": "para", "type": "tag", "attrs": {"style": "q2", "vid": "PRO 16:1"}, "items": [{"text": "but the answer of the tongue is from the LORD.", "type": "text", "attrs": {"verseId": "PRO.16.1", "verseOrgIds": ["PRO.16.1"]}}]}, {"name": "para", "type": "tag", "attrs": {"style": "q1"}, "items": [{"text": "All the ways of a man are clean in his own eyes,", "type": "text", "attrs": {"verseId": "PRO.16.2", "verseOrgIds": ["PRO.16.2"]}}]}, {"name": "para", "type": "tag", "attrs": {"style": "q2", "vid": "PRO 16:2"}, "items": [{"text": "but the LORD weighs the motives.", "type": "text", "attrs": {"verseId": "PRO.16.2", "verseOrgIds": ["PRO.16.2"]}}]}, {"name": "para", "type": "tag", "attrs": {"style": "q1"}, "items": [{"text": "Commit your deeds to the LORD,", "type": "text", "attrs": {"verseId": "PRO.16.3", "verseOrgIds": ["PRO.16.3"]}}]}, {"name": "para", "type": "tag", "attrs": {"style": "q2", "vid": "PRO 16:3"}, "items": [{"text": "and your plans shall succeed.", "type": "text", "attrs": {"verseId": "PRO.16.3", "verseOrgIds": ["PRO.16.3"]}}]}, {"name": "para", "type": "tag", "attrs": {"style": "q1"}, "items": [{"text": "The LORD has made everything for its own end\u2014", "type": "text", "attrs": {"verseId": "PRO.16.4", "verseOrgIds": ["PRO.16.4"]}}]}, {"name": "para", "type": "tag", "attrs": {"style": "q2", "vid": "PRO 16:4"}, "items": [{"text": "yes, even the wicked for the day of evil.", "type": "text", "attrs": {"verseId": "PRO.16.4", "verseOrgIds": ["PRO.16.4"]}}]}, {"name": "para", "type": "tag", "attrs": {"style": "q1"}, "items": [{"text": "Everyone who is proud in heart is an abomination to the LORD;", "type": "text", "attrs": {"verseId": "PRO.16.5", "verseOrgIds": ["PRO.16.5"]}}]}, {"name": "para", "type": "tag", "attrs": {"style": "q2", "vid": "PRO 16:5"}, "items": [{"text": "they shall certainly not be unpunished.", "type": "text", "attrs": {"verseId": "PRO.16.5", "verseOrgIds": ["PRO.16.5"]}}]}, {"name": "para", "type": "tag", "attrs": {"style": "q1"}, "items": [{"text": "By mercy and truth iniquity is atoned for.", "type": "text", "attrs": {"verseId": "PRO.16.6", "verseOrgIds": ["PRO.16.6"]}}]}, {"name": "para", "type": "tag", "attrs": {"style": "q2", "vid": "PRO 16:6"}, "items": [{"text": "By the fear of the LORD men depart from evil.", "type": "text", "attrs": {"verseId": "PRO.16.6", "verseOrgIds": ["PRO.16.6"]}}]}, {"name": "para", "type": "tag", "attrs": {"style": "q1"}, "items": [{"text": "When a man\u2019s ways please the LORD,", "type": "text", "attrs": {"verseId": "PRO.16.7", "verseOrgIds": ["PRO.16.7"]}}]}, {"name": "para", "type": "tag", "attrs": {"style": "q2", "vid": "PRO 16:7"}, "items": [{"text": "he makes even his enemies to be at peace with him.", "type": "text", "attrs": {"verseId": "PRO.16.7", "verseOrgIds": ["PRO.16.7"]}}]}, {"name": "para", "type": "tag", "attrs": {"style": "q1"}, "items": [{"text": "Better is a little with righteousness,", "type": "text", "attrs": {"verseId": "PRO.16.8", "verseOrgIds": ["PRO.16.8"]}}]}, {"name": "para", "type": "tag", "attrs": {"style": "q2", "vid": "PRO 16:8"}, "items": [{"text": "than great revenues with injustice.", "type": "text", "attrs": {"verseId": "PRO.16.8", "verseOrgIds": ["PRO.16.8"]}}]}, {"name": "para", "type": "tag", "attrs": {"style": "q1"}, "items": [{"text": "A man\u2019s heart plans his course,", "type": "text", "attrs": {"verseId": "PRO.16.9", "verseOrgIds": ["PRO.16.9"]}}]}, {"name": "para", "type": "tag", "attrs": {"style": "q2", "vid": "PRO 16:9"}, "items": [{"text": "but the LORD directs his steps.", "type": "text", "attrs": {"verseId": "PRO.16.9", "verseOrgIds": ["PRO.16.9"]}}]}, {"name": "para", "type": "tag", "attrs": {"style": "q1"}, "items": [{"text": "Inspired judgments are on the lips of the king.", "type": "text", "attrs": {"verseId": "PRO.16.10", "verseOrgIds": ["PRO.16.10"]}}]}, {"name": "para", "type": "tag", "attrs": {"style": "q2", "vid": "PRO 16:10"}, "items": [{"text": "He shall not betray his mouth.", "type": "text", "attrs": {"verseId": "PRO.16.10", "verseOrgIds": ["PRO.16.10"]}}]}, {"name": "para", "type": "tag", "attrs": {"style": "q1"}, "items": [{"text": "Honest balances and scales are the LORD\u2019s;", "type": "text", "attrs": {"verseId": "PRO.16.11", "verseOrgIds": ["PRO.16.11"]}}]}, {"name": "para", "type": "tag", "attrs": {"style": "q2", "vid": "PRO 16:11"}, "items": [{"text": "all the weights in the bag are his work.", "type": "text", "attrs": {"verseId": "PRO.16.11", "verseOrgIds": ["PRO.16.11"]}}]}, {"name": "para", "type": "tag", "attrs": {"style": "q1"}, "items": [{"text": "It is an abomination for kings to do wrong,", "type": "text", "attrs": {"verseId": "PRO.16.12", "verseOrgIds": ["PRO.16.12"]}}]}, {"name": "para", "type": "tag", "attrs": {"style": "q2", "vid": "PRO 16:12"}, "items": [{"text": "for the throne is established by righteousness.", "type": "text", "attrs": {"verseId": "PRO.16.12", "verseOrgIds": ["PRO.16.12"]}}]}, {"name": "para", "type": "tag", "attrs": {"style": "q1"}, "items": [{"text": "Righteous lips are the delight of kings.", "type": "text", "attrs": {"verseId": "PRO.16.13", "verseOrgIds": ["PRO.16.13"]}}]}, {"name": "para", "type": "tag", "attrs": {"style": "q2", "vid": "PRO 16:13"}, "items": [{"text": "They value one who speaks the truth.", "type": "text", "attrs": {"verseId": "PRO.16.13", "verseOrgIds": ["PRO.16.13"]}}]}, {"name": "para", "type": "tag", "attrs": {"style": "q1"}, "items": [{"text": "The king\u2019s wrath is a messenger of death,", "type": "text", "attrs": {"verseId": "PRO.16.14", "verseOrgIds": ["PRO.16.14"]}}]}, {"name": "para", "type": "tag", "attrs": {"style": "q2", "vid": "PRO 16:14"}, "items": [{"text": "but a wise man will pacify it.", "type": "text", "attrs": {"verseId": "PRO.16.14", "verseOrgIds": ["PRO.16.14"]}}]}, {"name": "para", "type": "tag", "attrs": {"style": "q1"}, "items": [{"text": "In the light of the king\u2019s face is life.", "type": "text", "attrs": {"verseId": "PRO.16.15", "verseOrgIds": ["PRO.16.15"]}}]}, {"name": "para", "type": "tag", "attrs": {"style": "q2", "vid": "PRO 16:15"}, "items": [{"text": "His favor is like a cloud of the spring rain.", "type": "text", "attrs": {"verseId": "PRO.16.15", "verseOrgIds": ["PRO.16.15"]}}]}, {"name": "para", "type": "tag", "attrs": {"style": "q1"}, "items": [{"text": "How much better it is to get wisdom than gold!", "type": "text", "attrs": {"verseId": "PRO.16.16", "verseOrgIds": ["PRO.16.16"]}}]}, {"name": "para", "type": "tag", "attrs": {"style": "q2", "vid": "PRO 16:16"}, "items": [{"text": "Yes, to get understanding is to be chosen rather than silver.", "type": "text", "attrs": {"verseId": "PRO.16.16", "verseOrgIds": ["PRO.16.16"]}}]}, {"name": "para", "type": "tag", "attrs": {"style": "q1"}, "items": [{"text": "The highway of the upright is to depart from evil.", "type": "text", "attrs": {"verseId": "PRO.16.17", "verseOrgIds": ["PRO.16.17"]}}]}, {"name": "para", "type": "tag", "attrs": {"style": "q2", "vid": "PRO 16:17"}, "items": [{"text": "He who keeps his way preserves his soul.", "type": "text", "attrs": {"verseId": "PRO.16.17", "verseOrgIds": ["PRO.16.17"]}}]}, {"name": "para", "type": "tag", "attrs": {"style": "q1"}, "items": [{"text": "Pride goes before destruction,", "type": "text", "attrs": {"verseId": "PRO.16.18", "verseOrgIds": ["PRO.16.18"]}}]}, {"name": "para", "type": "tag", "attrs": {"style": "q2", "vid": "PRO 16:18"}, "items": [{"text": "and an arrogant spirit before a fall.", "type": "text", "attrs": {"verseId": "PRO.16.18", "verseOrgIds": ["PRO.16.18"]}}]}, {"name": "para", "type": "tag", "attrs": {"style": "q1"}, "items": [{"text": "It is better to be of a lowly spirit with the poor,", "type": "text", "attrs": {"verseId": "PRO.16.19", "verseOrgIds": ["PRO.16.19"]}}]}, {"name": "para", "type": "tag", "attrs": {"style": "q2", "vid": "PRO 16:19"}, "items": [{"text": "than to divide the plunder with the proud.", "type": "text", "attrs": {"verseId": "PRO.16.19", "verseOrgIds": ["PRO.16.19"]}}]}, {"name": "para", "type": "tag", "attrs": {"style": "q1"}, "items": [{"text": "He who heeds the Word finds prosperity.", "type": "text", "attrs": {"verseId": "PRO.16.20", "verseOrgIds": ["PRO.16.20"]}}]}, {"name": "para", "type": "tag", "attrs": {"style": "q2", "vid": "PRO 16:20"}, "items": [{"text": "Whoever trusts in the LORD is blessed.", "type": "text", "attrs": {"verseId": "PRO.16.20", "verseOrgIds": ["PRO.16.20"]}}]}, {"name": "para", "type": "tag", "attrs": {"style": "q1"}, "items": [{"text": "The wise in heart shall be called prudent.", "type": "text", "attrs": {"verseId": "PRO.16.21", "verseOrgIds": ["PRO.16.21"]}}]}, {"name": "para", "type": "tag", "attrs": {"style": "q2", "vid": "PRO 16:21"}, "items": [{"text": "Pleasantness of the lips promotes instruction.", "type": "text", "attrs": {"verseId": "PRO.16.21", "verseOrgIds": ["PRO.16.21"]}}]}, {"name": "para", "type": "tag", "attrs": {"style": "q1"}, "items": [{"text": "Understanding is a fountain of life to one who has it,", "type": "text", "attrs": {"verseId": "PRO.16.22", "verseOrgIds": ["PRO.16.22"]}}]}, {"name": "para", "type": "tag", "attrs": {"style": "q2", "vid": "PRO 16:22"}, "items": [{"text": "but the punishment of fools is their folly.", "type": "text", "attrs": {"verseId": "PRO.16.22", "verseOrgIds": ["PRO.16.22"]}}]}, {"name": "para", "type": "tag", "attrs": {"style": "q1"}, "items": [{"text": "The heart of the wise instructs his mouth,", "type": "text", "attrs": {"verseId": "PRO.16.23", "verseOrgIds": ["PRO.16.23"]}}]}, {"name": "para", "type": "tag", "attrs": {"style": "q2", "vid": "PRO 16:23"}, "items": [{"text": "and adds learning to his lips.", "type": "text", "attrs": {"verseId": "PRO.16.23", "verseOrgIds": ["PRO.16.23"]}}]}, {"name": "para", "type": "tag", "attrs": {"style": "q1"}, "items": [{"text": "Pleasant words are a honeycomb,", "type": "text", "attrs": {"verseId": "PRO.16.24", "verseOrgIds": ["PRO.16.24"]}}]}, {"name": "para", "type": "tag", "attrs": {"style": "q2", "vid": "PRO 16:24"}, "items": [{"text": "sweet to the soul, and health to the bones.", "type": "text", "attrs": {"verseId": "PRO.16.24", "verseOrgIds": ["PRO.16.24"]}}]}, {"name": "para", "type": "tag", "attrs": {"style": "q1"}, "items": [{"text": "There is a way which seems right to a man,", "type": "text", "attrs": {"verseId": "PRO.16.25", "verseOrgIds": ["PRO.16.25"]}}]}, {"name": "para", "type": "tag", "attrs": {"style": "q2", "vid": "PRO 16:25"}, "items": [{"text": "but in the end it leads to death.", "type": "text", "attrs": {"verseId": "PRO.16.25", "verseOrgIds": ["PRO.16.25"]}}]}, {"name": "para", "type": "tag", "attrs": {"style": "q1"}, "items": [{"text": "The appetite of the laboring man labors for him,", "type": "text", "attrs": {"verseId": "PRO.16.26", "verseOrgIds": ["PRO.16.26"]}}]}, {"name": "para", "type": "tag", "attrs": {"style": "q2", "vid": "PRO 16:26"}, "items": [{"text": "for his mouth urges him on.", "type": "text", "attrs": {"verseId": "PRO.16.26", "verseOrgIds": ["PRO.16.26"]}}]}, {"name": "para", "type": "tag", "attrs": {"style": "q1"}, "items": [{"text": "A worthless man devises mischief.", "type": "text", "attrs": {"verseId": "PRO.16.27", "verseOrgIds": ["PRO.16.27"]}}]}, {"name": "para", "type": "tag", "attrs": {"style": "q2", "vid": "PRO 16:27"}, "items": [{"text": "His speech is like a scorching fire.", "type": "text", "attrs": {"verseId": "PRO.16.27", "verseOrgIds": ["PRO.16.27"]}}]}, {"name": "para", "type": "tag", "attrs": {"style": "q1"}, "items": [{"text": "A perverse man stirs up strife.", "type": "text", "attrs": {"verseId": "PRO.16.28", "verseOrgIds": ["PRO.16.28"]}}]}, {"name": "para", "type": "tag", "attrs": {"style": "q2", "vid": "PRO 16:28"}, "items": [{"text": "A whisperer separates close friends.", "type": "text", "attrs": {"verseId": "PRO.16.28", "verseOrgIds": ["PRO.16.28"]}}]}, {"name": "para", "type": "tag", "attrs": {"style": "q1"}, "items": [{"text": "A man of violence entices his neighbor,", "type": "text", "attrs": {"verseId": "PRO.16.29", "verseOrgIds": ["PRO.16.29"]}}]}, {"name": "para", "type": "tag", "attrs": {"style": "q2", "vid": "PRO 16:29"}, "items": [{"text": "and leads him in a way that is not good.", "type": "text", "attrs": {"verseId": "PRO.16.29", "verseOrgIds": ["PRO.16.29"]}}]}, {"name": "para", "type": "tag", "attrs": {"style": "q1"}, "items": [{"text": "One who winks his eyes to plot perversities,", "type": "text", "attrs": {"verseId": "PRO.16.30", "verseOrgIds": ["PRO.16.30"]}}]}, {"name": "para", "type": "tag", "attrs": {"style": "q2", "vid": "PRO 16:30"}, "items": [{"text": "one who compresses his lips, is bent on evil.", "type": "text", "attrs": {"verseId": "PRO.16.30", "verseOrgIds": ["PRO.16.30"]}}]}, {"name": "para", "type": "tag", "attrs": {"style": "q1"}, "items": [{"text": "Gray hair is a crown of glory.", "type": "text", "attrs": {"verseId": "PRO.16.31", "verseOrgIds": ["PRO.16.31"]}}]}, {"name": "para", "type": "tag", "attrs": {"style": "q2", "vid": "PRO 16:31"}, "items": [{"text": "It is attained by a life of righteousness.", "type": "text", "attrs": {"verseId": "PRO.16.31", "verseOrgIds": ["PRO.16.31"]}}]}, {"name": "para", "type": "tag", "attrs": {"style": "q1"}, "items": [{"text": "One who is slow to anger is better than the mighty;", "type": "text", "attrs": {"verseId": "PRO.16.32", "verseOrgIds": ["PRO.16.32"]}}]}, {"name": "para", "type": "tag", "attrs": {"style": "q2", "vid": "PRO 16:32"}, "items": [{"text": "one who rules his spirit, than he who takes a city.", "type": "text", "attrs": {"verseId": "PRO.16.32", "verseOrgIds": ["PRO.16.32"]}}]}, {"name": "para", "type": "tag", "attrs": {"style": "q1"}, "items": [{"text": "The lot is cast into the lap,", "type": "text", "attrs": {"verseId": "PRO.16.33", "verseOrgIds": ["PRO.16.33"]}}]}, {"name": "para", "type": "tag", "attrs": {"style": "q2", "vid": "PRO 16:33"}, "items": [{"text": "but its every decision is from the LORD.", "type": "text", "attrs": {"verseId": "PRO.16.33", "verseOrgIds": ["PRO.16.33"]}}]}], "next": {"id": "PRO.17", "number": "17", "bookId": "PRO"}, "previous": {"id": "PRO.15", "number": "15", "bookId": "PRO"}}}}