{"_default": {"1": {"id": "PSA.130", "bibleId": "bf8f1c7f3f9045a5-01", "number": "130", "bookId": "PSA", "reference": "Psalms 130", "copyright": "PUBLIC DOMAIN", "content": [{"name": "para", "type": "tag", "attrs": {"style": "p"}, "items": [{"text": "A Song of Ascents. Out of the depths have I called Thee, O LORD. ", "type": "text", "attrs": {"verseId": "PSA.130.1", "verseOrgIds": ["PSA.130.1"]}}, {"text": "Lord, hearken unto my voice; let Thine ears be attentive to the voice of my supplications. ", "type": "text", "attrs": {"verseId": "PSA.130.2", "verseOrgIds": ["PSA.130.2"]}}, {"text": "If Thou, LORD, shouldest mark iniquities, O Lord, who could stand? ", "type": "text", "attrs": {"verseId": "PSA.130.3", "verseOrgIds": ["PSA.130.3"]}}, {"text": "For with Thee there is forgiveness, that Thou mayest be feared. ", "type": "text", "attrs": {"verseId": "PSA.130.4", "verseOrgIds": ["PSA.130.4"]}}, {"text": "I wait for the LORD, my soul doth wait, and in His word do I hope. ", "type": "text", "attrs": {"verseId": "PSA.130.5", "verseOrgIds": ["PSA.130.5"]}}, {"text": "My soul waiteth for the Lord, more than watchmen for the morning; yea, more than watchmen for the morning. ", "type": "text", "attrs": {"verseId": "PSA.130.6", "verseOrgIds": ["PSA.130.6"]}}, {"text": "O Israel, hope in the LORD; for with the LORD there is mercy, and with Him is plenteous redemption. ", "type": "text", "attrs": {"verseId": "PSA.130.7", "verseOrgIds": ["PSA.130.7"]}}, {"text": "And He will redeem Israel from all his iniquities.", "type": "text", "attrs": {"verseId": "PSA.130.8", "verseOrgIds": ["PSA.130.8"]}}]}], "next": {"id": "PSA.131", "number": "131", "bookId": "PSA"}, "previous": {"id": "PSA.129", "number": "129", "bookId": "PSA"}}}}